pretext/__init__.py
pretext/__main__.py
pretext/cli.py
pretext/codechat.py
pretext/constants.py
pretext/core/__init__.py
pretext/core/braille_format.py
pretext/core/pretext.py
pretext/logger.py
pretext/plastex/Alignment.jinja2s
pretext/plastex/Arrays.jinja2s
pretext/plastex/Bibliography.jinja2s
pretext/plastex/Boxes.jinja2s
pretext/plastex/Breaking.jinja2s
pretext/plastex/Crossref.jinja2s
pretext/plastex/Floats.jinja2s
pretext/plastex/FontSelection.jinja2s
pretext/plastex/Footnotes.jinja2s
pretext/plastex/Index.jinja2s
pretext/plastex/Lists.jinja2s
pretext/plastex/Pictures.jinja2s
pretext/plastex/Quotations.jinja2s
pretext/plastex/Sectioning.jinja2s
pretext/plastex/Sentences.jinja2s
pretext/plastex/Space.jinja2s
pretext/plastex/Tabbing.jinja2s
pretext/plastex/Themes/__init__.py
pretext/plastex/Themes/default/__init__.py
pretext/plastex/Themes/default/default-layout.jinja2
pretext/plastex/Themes/default/document-layout.jinja2
pretext/plastex/Thms.jinja2s
pretext/plastex/Verbatim.jinja2s
pretext/plastex/__init__.py
pretext/plastex/babel.jinja2s
pretext/plastex/graphicx.jinja2s
pretext/plastex/hyperref.jinja2s
pretext/plastex/lipsum.jinja2s
pretext/plastex/longtable.jinja2s
pretext/plastex/math.jinja2s
pretext/plastex/misc.jinja2s
pretext/plastex/natbib.jinja2s
pretext/plastex/p.jinja2s
pretext/plastex/subfig.jinja2s
pretext/plastex/textcomp.jinja2s
pretext/plastex/tikzcd.jinja2
pretext/plastex/tikzpicture.jinja2
pretext/plastex/url.jinja2s
pretext/plastex/wrapfig.jinja2s
pretext/project/__init__.py
pretext/project/generate.py
pretext/project/xml.py
pretext/resources/__init__.py
pretext/resources/core.zip
pretext/resources/pelican.zip
pretext/resources/resource_hash_table.json
pretext/resources/rs_cache.zip
pretext/resources/templates.zip
pretext/server.py
pretext/types.py
pretext/utils.py
pretext-2.36.0.dist-info/LICENSE
pretext-2.36.0.dist-info/METADATA
pretext-2.36.0.dist-info/WHEEL
pretext-2.36.0.dist-info/entry_points.txt
pretext-2.36.0.dist-info/RECORD
