Metadata-Version: 2.1
Name: pretext
Version: 2.36.0
Summary: A package to author, build, and deploy PreTeXt projects.
Home-page: https://pretextbook.org
License: GPL-3.0-or-later
Author: Oscar Levin
Author-email: oscar.levin@unco.edu
Requires-Python: >=3.10,<4.0
Classifier: License :: OSI Approved :: GNU General Public License v3 or later (GPLv3+)
Classifier: Programming Language :: Python :: 3
Classifier: Programming Language :: Python :: 3.10
Classifier: Programming Language :: Python :: 3.11
Classifier: Programming Language :: Python :: 3.12
Classifier: Programming Language :: Python :: 3.13
Provides-Extra: all
Provides-Extra: homepage
Provides-Extra: prefigure
Requires-Dist: GitPython (>=3,<4)
Requires-Dist: PyPDF2 (>=2.5,<2.6)
Requires-Dist: citeproc-py (>=0,<1)
Requires-Dist: click (>=8,<9)
Requires-Dist: click-log (>=0.4,<0.5)
Requires-Dist: coloraide (>=4,<5)
Requires-Dist: ghp-import (>=2,<3)
Requires-Dist: jinja2 (>=3,<4)
Requires-Dist: lxml (>=6,<7)
Requires-Dist: pdfCropMargins (>=1.0.9,<1.1.0)
Requires-Dist: pelican[markdown] (>=4.10,<5.0) ; extra == "homepage" or extra == "all"
Requires-Dist: plastex (>=3,<4)
Requires-Dist: playwright (>=1,<2)
Requires-Dist: prefig[text] (>=0.5.0,<0.6.0) ; extra == "prefigure" or extra == "all"
Requires-Dist: psutil (>=7,<8)
Requires-Dist: pyMuPDF (>=1.24,<2.0)
Requires-Dist: pydantic-xml (==2.14.3)
Requires-Dist: qrcode (>=7,<8)
Requires-Dist: requests (>=2,<3)
Requires-Dist: single-version (>=1,<2)
Project-URL: Repository, https://github.com/PreTeXtBook/pretext-cli
